qorp/__init__.py
qorp/encryption.py
qorp/frontend.py
qorp/messages.py
qorp/nodes.py
qorp/router.py
qorp/transports.py
qorp-0.0.0.dev0.dist-info/METADATA
qorp-0.0.0.dev0.dist-info/WHEEL
qorp-0.0.0.dev0.dist-info/top_level.txt
qorp-0.0.0.dev0.dist-info/RECORD
